physt/__init__.py
physt/_bin_utils.py
physt/_construction.py
physt/_facade.py
physt/_util.py
physt/binnings.py
physt/cli.py
physt/config.py
physt/histogram1d.py
physt/histogram_base.py
physt/histogram_collection.py
physt/histogram_nd.py
physt/py.typed
physt/special_histograms.py
physt/statistics.py
physt/types.py
physt/typing_aliases.py
physt/version.py
physt/compat/__init__.py
physt/compat/dask.py
physt/compat/geant4.py
physt/compat/pandas.py
physt/compat/polars.py
physt/compat/xarray.py
physt/examples/__init__.py
physt/examples/__main__.py
physt/examples/munros.csv
physt/helpers/__init__.py
physt/helpers/db.py
physt/io/__init__.py
physt/io/json.py
physt/io/root.py
physt/io/util.py
physt/io/version.py
physt/plotting/__init__.py
physt/plotting/ascii.py
physt/plotting/common.py
physt/plotting/folium.py
physt/plotting/matplotlib.py
physt/plotting/plotly.py
physt/plotting/vega.py
physt/testing/__init__.py
physt/testing/strategies.py
physt-0.9.0.dist-info/entry_points.txt
physt-0.9.0.dist-info/licenses/LICENSE
physt-0.9.0.dist-info/WHEEL
physt-0.9.0.dist-info/METADATA
physt-0.9.0.dist-info/RECORD
