Metadata-Version: 2.4
Name: physt
Version: 0.9.0
Summary: P(i/y)thon h(i/y)stograms.
Author-email: Jan Pipek <jan.pipek@gmail.com>
Requires-Python: >=3.9
Classifier: License :: OSI Approved :: MIT License
Classifier: Operating System :: OS Independent
Classifier: Intended Audience :: Developers
Classifier: Intended Audience :: Information Technology
Classifier: Intended Audience :: Science/Research
Classifier: Topic :: Scientific/Engineering
Classifier: Topic :: Software Development :: Libraries :: Python Modules
License-File: LICENSE
Requires-Dist: numpy>=1.25
Requires-Dist: packaging
Requires-Dist: typing_extensions
Requires-Dist: hypothesis>=6.96.1
Requires-Dist: click>=8.1.8
Requires-Dist: narwhals>=2.0.1
Requires-Dist: rich>=14.1.0
Requires-Dist: physt[astropy, dask, pandas, polars, xarray, matplotlib, plotly, folium] ; extra == "all"
Requires-Dist: astropy>=6.0 ; extra == "astropy"
Requires-Dist: dask[array]>=2023.0 ; extra == "dask"
Requires-Dist: folium ; extra == "folium"
Requires-Dist: matplotlib>=3.0 ; extra == "matplotlib"
Requires-Dist: pandas>=1.3 ; extra == "pandas"
Requires-Dist: plotly ; extra == "plotly"
Requires-Dist: polars>=1.0 ; extra == "polars"
Requires-Dist: physt[pandas] ; extra == "polars"
Requires-Dist: xarray ; extra == "xarray"
Provides-Extra: all
Provides-Extra: astropy
Provides-Extra: dask
Provides-Extra: folium
Provides-Extra: matplotlib
Provides-Extra: pandas
Provides-Extra: plotly
Provides-Extra: polars
Provides-Extra: xarray
